brainmaze_eeg/__init__.py
brainmaze_eeg/classifiers.py
brainmaze_eeg/crp.py
brainmaze_eeg/hypnogram.py
brainmaze_eeg/preprocessing.py
brainmaze_eeg/scikit_modules.py
brainmaze_eeg/features/__init__.py
brainmaze_eeg/features/dataset.py
brainmaze_eeg/features/feature_extraction.py
brainmaze_eeg/features/spectral_features.py
brainmaze_eeg/features/time_domain_features.py
brainmaze_eeg/features/utils.py
brainmaze_eeg/features/wave_detector.py
brainmaze_eeg/tests/__init__.py
brainmaze_eeg/tests/dummy_test.py
brainmaze_eeg/tests/test_preprocessing.py
brainmaze_eeg-0.1.6.dist-info/licenses/LICENSE
brainmaze_eeg-0.1.6.dist-info/METADATA
brainmaze_eeg-0.1.6.dist-info/WHEEL
brainmaze_eeg-0.1.6.dist-info/top_level.txt
brainmaze_eeg-0.1.6.dist-info/RECORD
