Metadata-Version: 2.4
Name: brainmaze-eeg
Version: 0.1.6
Summary: BrainMaze: Brain Electrophysiology, Behavior and Dynamics Analysis Toolbox
Home-page: https://github.com/bnelair/brainmaze_eeg
Author: Filip Mivalt
Author-email: mivalt.filip@mayo.edu
License: BSD-3-Clause
Classifier: Topic :: Scientific/Engineering :: Medical Science Apps.
Classifier: Development Status :: 3 - Alpha
Classifier: Programming Language :: Python
Classifier: Programming Language :: Python :: 3
Classifier: Programming Language :: Python :: 3.9
Classifier: Programming Language :: Python :: 3.10
Classifier: Programming Language :: Python :: 3.11
Classifier: Programming Language :: Python :: 3.12
Classifier: Operating System :: OS Independent
Classifier: License :: OSI Approved :: BSD License
Classifier: Intended Audience :: Healthcare Industry
Classifier: Intended Audience :: Science/Research
Requires-Python: >=3.9.0
License-File: LICENSE
Requires-Dist: setuptools>=61
Requires-Dist: setuptools_scm
Requires-Dist: sphinx
Requires-Dist: sphinx_book_theme
Requires-Dist: brainmaze_utils
Requires-Dist: pytest
Requires-Dist: numpy
Requires-Dist: pandas
Requires-Dist: pytz
Requires-Dist: python-dateutil
Requires-Dist: scikit-learn
Requires-Dist: scipy
Requires-Dist: tqdm
Dynamic: author
Dynamic: author-email
Dynamic: classifier
Dynamic: description
Dynamic: description-content-type
Dynamic: home-page
Dynamic: license
Dynamic: license-file
Dynamic: requires-dist
Dynamic: requires-python
Dynamic: summary
